filesystem_database/__init__.py
filesystem_database-1.0.4.dist-info/LICENSE
filesystem_database-1.0.4.dist-info/METADATA
filesystem_database-1.0.4.dist-info/WHEEL
filesystem_database-1.0.4.dist-info/top_level.txt
filesystem_database-1.0.4.dist-info/RECORD
