Metadata-Version: 2.1
Name: filesystem-database
Version: 1.0.4
Summary: A relatively simple multilayered database built on top of standard file systems.
Home-page: https://github.com/AwesomeCronk/filesystem-database
Author: AwesomeCronk
Author-email: awesomecronk@gmail.com
License: UNKNOWN
Project-URL: Bug Tracker, https://github.com/AwesoemCronk/filesystem-database/issues
Platform: UNKNOWN
Classifier: Programming Language :: Python :: 3
Classifier: License :: OSI Approved :: MIT License
Classifier: Operating System :: OS Independent
Requires-Python: >=3.6
License-File: LICENSE
